ft_package/__init__.py
ft_package/count.py
ft_package/utils.py
jfatfat_package-0.0.3.dist-info/LICENSE
jfatfat_package-0.0.3.dist-info/METADATA
jfatfat_package-0.0.3.dist-info/WHEEL
jfatfat_package-0.0.3.dist-info/top_level.txt
jfatfat_package-0.0.3.dist-info/RECORD
