Metadata-Version: 2.2
Name: jfatfat_package
Version: 0.0.3
Summary: A simple utility package
Home-page: https://github.com/jihadfatfat99/Python-Piscine/00/ex09/ft-package
Author: Jihad Fatfat
Author-email: jihadmohfatfat1999@gmail.com
Classifier: Programming Language :: Python :: 3
Classifier: License :: OSI Approved :: MIT License
Classifier: Operating System :: OS Independent
Requires-Python: >=3.6
License-File: LICENSE
Dynamic: author
Dynamic: author-email
Dynamic: classifier
Dynamic: description
Dynamic: description-content-type
Dynamic: home-page
Dynamic: requires-python
Dynamic: summary
